seqsim/__init__.py
seqsim/common.py
seqsim/compression.py
seqsim/edit.py
seqsim/ngrams.py
seqsim/sequence.py
seqsim/token.py
seqsim-0.3.2.dist-info/AUTHORS.md
seqsim-0.3.2.dist-info/LICENSE
seqsim-0.3.2.dist-info/METADATA
seqsim-0.3.2.dist-info/WHEEL
seqsim-0.3.2.dist-info/top_level.txt
seqsim-0.3.2.dist-info/RECORD
