Metadata-Version: 2.1
Name: seqsim
Version: 0.3.2
Summary: Library for computing measures of similarity for sequences of hashable data types
Home-page: https://github.com/tresoldi/seqsim
Author: Tiago Tresoldi
Author-email: tiago.tresoldi@lingfil.uu.se
License: MIT
Keywords: sequence similarity,sequence distance,string similarity,string distance
Platform: UNKNOWN
Classifier: License :: OSI Approved :: MIT License
Classifier: Operating System :: OS Independent
Classifier: Programming Language :: Python :: 3
Classifier: Topic :: Software Development :: Libraries
Requires-Python: >=3.6
Requires-Dist: numpy
Requires-Dist: tabulate
Requires-Dist: textdistance
Provides-Extra: dev
Requires-Dist: black ; extra == 'dev'
Requires-Dist: flake8 ; extra == 'dev'
Requires-Dist: twine ; extra == 'dev'
Requires-Dist: wheel ; extra == 'dev'
Provides-Extra: test
Requires-Dist: pytest ; extra == 'test'
